dotez/__init__.py
dotez/cli.py
dotez/config.py
dotez/example.conf
dotez/__pycache__/__init__.cpython-36.pyc
dotez/__pycache__/config.cpython-36.pyc
dotez/core/__init__.py
dotez/core/dotez.py
dotez/core/__pycache__/__init__.cpython-36.pyc
dotez/core/__pycache__/dotez.cpython-36.pyc
dotez-0.0.3.dist-info/LICENSE
dotez-0.0.3.dist-info/METADATA
dotez-0.0.3.dist-info/WHEEL
dotez-0.0.3.dist-info/entry_points.txt
dotez-0.0.3.dist-info/top_level.txt
dotez-0.0.3.dist-info/RECORD
